cooplan_integration_test_boilerplate/__init__.py
cooplan_integration_test_boilerplate/test.py
cooplan_integration_test_boilerplate-0.0.3.dist-info/LICENSE
cooplan_integration_test_boilerplate-0.0.3.dist-info/METADATA
cooplan_integration_test_boilerplate-0.0.3.dist-info/WHEEL
cooplan_integration_test_boilerplate-0.0.3.dist-info/top_level.txt
cooplan_integration_test_boilerplate-0.0.3.dist-info/RECORD
