Metadata-Version: 2.1
Name: cooplan-integration-test-boilerplate
Version: 0.0.3
Summary: Boilerplate for Cooplan's integration tests
Author-email: Gabriel Amihalachioaie <gabriel@simpleg.eu>
Project-URL: Homepage, https://github.com/simple0x47/cooplan-integration-test-boilerplate
Classifier: Programming Language :: Python :: 3
Classifier: License :: OSI Approved :: MIT License
Classifier: Operating System :: OS Independent
Requires-Python: >=3.9
License-File: LICENSE
Requires-Dist: pymongo[srv] (>=4.3.3)
